pyfortiassetmgmt/__init__.py
pyfortiassetmgmt/core/__init__.py
pyfortiassetmgmt/core/api.py
pyfortiassetmgmt/core/fortiassetmgmt.py
pyfortiassetmgmt/models/__init__.py
pyfortiassetmgmt/models/contracts.py
pyfortiassetmgmt/models/folders.py
pyfortiassetmgmt/models/licenses.py
pyfortiassetmgmt/models/products.py
pyfortiassetmgmt/models/services.py
pyfortiassetmgmt-1.0.1.dist-info/LICENSE
pyfortiassetmgmt-1.0.1.dist-info/METADATA
pyfortiassetmgmt-1.0.1.dist-info/WHEEL
pyfortiassetmgmt-1.0.1.dist-info/top_level.txt
pyfortiassetmgmt-1.0.1.dist-info/RECORD
